package/__init__.py
package/outliers.py
Tarit_Outlier_Removal-1.0.0.dist-info/LICENSE.txt
Tarit_Outlier_Removal-1.0.0.dist-info/METADATA
Tarit_Outlier_Removal-1.0.0.dist-info/WHEEL
Tarit_Outlier_Removal-1.0.0.dist-info/entry_points.txt
Tarit_Outlier_Removal-1.0.0.dist-info/top_level.txt
Tarit_Outlier_Removal-1.0.0.dist-info/RECORD
