Metadata-Version: 2.1
Name: Tarit-Outlier-Removal
Version: 1.0.0
Summary: Outlier Removal
Home-page: UNKNOWN
Author: Tarit Kandpal
Author-email: taritkandpal@gmail.com
License: UNKNOWN
Platform: UNKNOWN
Classifier: Programming Language :: Python :: 3
Classifier: License :: OSI Approved :: MIT License
Classifier: Operating System :: OS Independent
Requires-Python: >=3.6
Requires-Dist: requests
